agenticlayer/__init__.py
agenticlayer/agent_to_a2a.py
agenticlayer/callback_tracer_plugin.py
agenticlayer/otel.py
agentic_layer_sdk_adk-0.5.0.dist-info/METADATA
agentic_layer_sdk_adk-0.5.0.dist-info/WHEEL
agentic_layer_sdk_adk-0.5.0.dist-info/RECORD
