Metadata-Version: 2.4
Name: agentic-layer-sdk-adk
Version: 0.5.0
Requires-Python: >=3.12
Requires-Dist: google-adk[a2a]
Requires-Dist: litellm
Requires-Dist: openinference-instrumentation-google-adk
Requires-Dist: opentelemetry-exporter-otlp-proto-http
Requires-Dist: opentelemetry-instrumentation-httpx
Requires-Dist: opentelemetry-instrumentation-starlette
